contribution_plan/__init__.py
contribution_plan/admin.py
contribution_plan/apps.py
contribution_plan/mixins.py
contribution_plan/models.py
contribution_plan/schema.py
contribution_plan/services.py
contribution_plan/urls.py
contribution_plan/utils.py
contribution_plan/views.py
contribution_plan/gql/__init__.py
contribution_plan/gql/gql_types.py
contribution_plan/gql/util.py
contribution_plan/gql/gql_mutations/__init__.py
contribution_plan/gql/gql_mutations/contribution_plan_bundle_details_mutations.py
contribution_plan/gql/gql_mutations/contribution_plan_bundle_mutations.py
contribution_plan/gql/gql_mutations/contribution_plan_mutations.py
contribution_plan/gql/gql_mutations/input_types.py
contribution_plan/gql/gql_mutations/payment_plan_mutations.py
contribution_plan/migrations/0001_initial.py
contribution_plan/migrations/0001_squashed_0013_rebase.py
contribution_plan/migrations/0002_auto_20201204_1353.py
contribution_plan/migrations/0003_auto_20201204_1439.py
contribution_plan/migrations/0004_auto_20201217_0946.py
contribution_plan/migrations/0005_contributionplanbundlemutation_contributionplanmutation.py
contribution_plan/migrations/0006_auto_20210118_1349.py
contribution_plan/migrations/0007_auto_20210217_1302.py
contribution_plan/migrations/0008_historicalpaymentplan_paymentplan.py
contribution_plan/migrations/0009_contributionplan_roles_for_admin.py
contribution_plan/migrations/0010_payment_plan_roles_for_admin.py
contribution_plan/migrations/0011_auto_20230126_0903.py
contribution_plan/migrations/0012_benefit_plan_generic_fk.py
contribution_plan/migrations/0013_alter_contributionplan_date_created_and_more.py
contribution_plan/migrations/__init__.py
contribution_plan/tests/__init__.py
contribution_plan/tests/helpers.py
contribution_plan/tests/helpers_tests.py
contribution_plan/tests/gql_tests/__init__.py
contribution_plan/tests/gql_tests/mutations_cp_tests.py
contribution_plan/tests/gql_tests/mutations_cpb_tests.py
openimis_be_contribution_plan-1.10.0.dist-info/licenses/LICENSE.md
openimis_be_contribution_plan-1.10.0.dist-info/METADATA
openimis_be_contribution_plan-1.10.0.dist-info/WHEEL
openimis_be_contribution_plan-1.10.0.dist-info/top_level.txt
openimis_be_contribution_plan-1.10.0.dist-info/RECORD
